brawlstarsapi/__init__.py
brawlstarsapi/brawlstarsapi.egg-info/PKG-INFO
brawlstarsapi/brawlstarsapi.egg-info/SOURCES.txt
brawlstarsapi/brawlstarsapi.egg-info/dependency_links.txt
brawlstarsapi/brawlstarsapi.egg-info/top_level.txt
brawlstarsapi/client.py
brawlstarsapi/utils.py
brawlstarsapi-0.1.0.dist-info/LICENSE
brawlstarsapi-0.1.0.dist-info/WHEEL
brawlstarsapi-0.1.0.dist-info/METADATA
brawlstarsapi-0.1.0.dist-info/RECORD
